keylocker/__init__.py
keylocker/__main__.py
keylocker/requirements.txt
keylocker-0.4.7.dist-info/METADATA
keylocker-0.4.7.dist-info/WHEEL
keylocker-0.4.7.dist-info/entry_points.txt
keylocker-0.4.7.dist-info/RECORD
