Metadata-Version: 2.3
Name: keylocker
Version: 0.4.7
Summary: Library with the CLI to save the encrypted secrets in the configuration file, but a transparent read and write the new settings in the app.
License: MIT
Author: vpuhoff
Author-email: vpuhoff@live.ru
Requires-Python: >=3.10
Classifier: Programming Language :: Python :: 3
Classifier: License :: OSI Approved :: MIT License
Classifier: Operating System :: OS Independent
Classifier: Development Status :: 4 - Beta
Classifier: Intended Audience :: Developers
Classifier: Topic :: Software Development :: Libraries :: Python Modules
Classifier: Topic :: Utilities
